modeci_mdf/__init__.py
modeci_mdf/execution_engine.py
modeci_mdf/full_translator.py
modeci_mdf/mdf.py
modeci_mdf/utils.py
modeci_mdf/functions/__init__.py
modeci_mdf/functions/ddm.py
modeci_mdf/functions/onnx.py
modeci_mdf/functions/standard.py
modeci_mdf/functions/actr/__init__.py
modeci_mdf/functions/actr/ccm/__init__.py
modeci_mdf/functions/actr/ccm/buffer.py
modeci_mdf/functions/actr/ccm/dm.py
modeci_mdf/functions/actr/ccm/logger.py
modeci_mdf/functions/actr/ccm/model.py
modeci_mdf/functions/actr/ccm/pattern.py
modeci_mdf/functions/actr/ccm/scheduler.py
modeci_mdf/interfaces/__init__.py
modeci_mdf/interfaces/actr/__init__.py
modeci_mdf/interfaces/actr/importer.py
modeci_mdf/interfaces/graphviz/__init__.py
modeci_mdf/interfaces/graphviz/exporter.py
modeci_mdf/interfaces/keras/__init__.py
modeci_mdf/interfaces/keras/importer.py
modeci_mdf/interfaces/neuroml/__init__.py
modeci_mdf/interfaces/neuroml/exporter.py
modeci_mdf/interfaces/neuroml/syn_definitions.xml
modeci_mdf/interfaces/onnx/__init__.py
modeci_mdf/interfaces/onnx/exporter.py
modeci_mdf/interfaces/onnx/importer.py
modeci_mdf/interfaces/pytorch/__init__.py
modeci_mdf/interfaces/pytorch/builtins.py
modeci_mdf/interfaces/pytorch/exporter.py
modeci_mdf/interfaces/pytorch/importer.py
modeci_mdf/interfaces/pytorch/mod_torch_builtins.py
modeci_mdf-0.4.13.dist-info/licenses/LICENSE
modeci_mdf-0.4.13.dist-info/METADATA
modeci_mdf-0.4.13.dist-info/WHEEL
modeci_mdf-0.4.13.dist-info/top_level.txt
modeci_mdf-0.4.13.dist-info/RECORD
