Metadata-Version: 2.4
Name: modeci-mdf
Version: 0.4.13
Summary: ModECI (Model Exchange and Convergence Initiative) Model Description Format
Author-email: ModECI contributors <p.gleeson@gmail.com>
Maintainer-email: ModECI contributors <p.gleeson@gmail.com>
License: LGPLv3
Project-URL: Homepage, https://www.modeci.org
Project-URL: Repository, https://github.com/ModECI/MDF
Project-URL: Documentation, https://mdf.readthedocs.io
Keywords: scientific computing,modeling,neuroscience
Classifier: Intended Audience :: Science/Research
Classifier: License :: OSI Approved :: GNU Lesser General Public License v3 (LGPLv3)
Classifier: Natural Language :: English
Classifier: Operating System :: OS Independent
Classifier: Programming Language :: Python :: 3.8
Classifier: Topic :: Scientific/Engineering
Classifier: Intended Audience :: Science/Research
Classifier: Programming Language :: Python
Classifier: Programming Language :: Python :: 3
Classifier: Programming Language :: Python :: 3 :: Only
Classifier: Programming Language :: Python :: 3.10
Classifier: Programming Language :: Python :: 3.11
Classifier: Programming Language :: Python :: 3.12
Classifier: Programming Language :: Python :: 3.13
Classifier: Topic :: Scientific/Engineering
Classifier: Topic :: Software Development
Classifier: Typing :: Typed
Requires-Python: >=3.9
License-File: LICENSE
Requires-Dist: graph_scheduler>=1.1.1
Requires-Dist: numpy
Requires-Dist: matplotlib
Requires-Dist: graphviz
Requires-Dist: h5py
Requires-Dist: onnxruntime
Requires-Dist: onnx
Requires-Dist: skl2onnx
Requires-Dist: attrs>=21.1.0
Requires-Dist: cattrs
Requires-Dist: modelspec<0.4,>=0.3.0
Requires-Dist: glom
Provides-Extra: psyneulink
Requires-Dist: psyneulink>=0.15.3; extra == "psyneulink"
Provides-Extra: neuroml
Requires-Dist: pyNeuroML>=1.0.10; extra == "neuroml"
Requires-Dist: neuromllite>=0.5.6; extra == "neuroml"
Requires-Dist: PyNN>=0.10.1; extra == "neuroml"
Provides-Extra: neuroml-simulators
Requires-Dist: neuron; extra == "neuroml-simulators"
Provides-Extra: tensorflow
Requires-Dist: tensorflow>=2.16.0; extra == "tensorflow"
Requires-Dist: keras_visualizer; extra == "tensorflow"
Requires-Dist: pydot; extra == "tensorflow"
Provides-Extra: test
Requires-Dist: pytest; extra == "test"
Requires-Dist: pytest-benchmark; extra == "test"
Requires-Dist: pytest-mock; extra == "test"
Requires-Dist: setuptools; extra == "test"
Provides-Extra: optional
Requires-Dist: torchviz; extra == "optional"
Requires-Dist: netron; extra == "optional"
Requires-Dist: torch>=1.11.0; extra == "optional"
Requires-Dist: torchvision; extra == "optional"
Requires-Dist: h5py; extra == "optional"
Provides-Extra: all-except-psyneulink
Requires-Dist: modeci-mdf[tensorflow]; extra == "all-except-psyneulink"
Requires-Dist: modeci-mdf[optional]; extra == "all-except-psyneulink"
Requires-Dist: modeci-mdf[neuroml]; extra == "all-except-psyneulink"
Provides-Extra: all
Requires-Dist: modeci-mdf[all_except_psyneulink]; extra == "all"
Requires-Dist: modeci-mdf[psyneulink]; extra == "all"
Requires-Dist: modeci-mdf[neuroml_simulators]; extra == "all"
Dynamic: license-file
